Lingzu0dayWenkuFix1/README.md
Lingzu0dayWenkuFix1/__init__.py
Lingzu0dayWenkuFix1/__main__.py
Lingzu0dayWenkuFix1/file.epub
Lingzu0dayWenkuFix1/index.html
Lingzu0dayWenkuFix1/css/__init__.py
Lingzu0dayWenkuFix1/css/annotations.css
Lingzu0dayWenkuFix1/css/main.css
Lingzu0dayWenkuFix1/css/normalize.css
Lingzu0dayWenkuFix1/css/popup.css
Lingzu0dayWenkuFix1/font/__init__.py
Lingzu0dayWenkuFix1/font/fontello.eot
Lingzu0dayWenkuFix1/font/fontello.svg
Lingzu0dayWenkuFix1/font/fontello.ttf
Lingzu0dayWenkuFix1/font/fontello.woff
Lingzu0dayWenkuFix1/img/__init__.py
Lingzu0dayWenkuFix1/img/annotator-glyph-sprite.png
Lingzu0dayWenkuFix1/img/annotator-icon-sprite.png
Lingzu0dayWenkuFix1/img/apple-touch-icon.png
Lingzu0dayWenkuFix1/img/cancelfullscreen.png
Lingzu0dayWenkuFix1/img/close.png
Lingzu0dayWenkuFix1/img/fullscreen.png
Lingzu0dayWenkuFix1/img/loader.gif
Lingzu0dayWenkuFix1/img/menu-icon.png
Lingzu0dayWenkuFix1/img/save.png
Lingzu0dayWenkuFix1/img/saved.png
Lingzu0dayWenkuFix1/img/settings-s.png
Lingzu0dayWenkuFix1/img/settings.png
Lingzu0dayWenkuFix1/img/star.png
Lingzu0dayWenkuFix1/js/__init__.py
Lingzu0dayWenkuFix1/js/epub.js
Lingzu0dayWenkuFix1/js/epub.min.js
Lingzu0dayWenkuFix1/js/epub.min.map
Lingzu0dayWenkuFix1/js/hooks.min.js
Lingzu0dayWenkuFix1/js/hooks.min.map
Lingzu0dayWenkuFix1/js/reader.js
Lingzu0dayWenkuFix1/js/reader.js.map
Lingzu0dayWenkuFix1/js/reader.min.js
Lingzu0dayWenkuFix1/js/reader.min.map
Lingzu0dayWenkuFix1/js/hooks/__init__.py
Lingzu0dayWenkuFix1/js/hooks/extensions/__init__.py
Lingzu0dayWenkuFix1/js/hooks/extensions/highlight.js
Lingzu0dayWenkuFix1/js/libs/__init__.py
Lingzu0dayWenkuFix1/js/libs/jquery.min.js
Lingzu0dayWenkuFix1/js/libs/localforage.min.js
Lingzu0dayWenkuFix1/js/libs/screenfull.js
Lingzu0dayWenkuFix1/js/libs/screenfull.min.js
Lingzu0dayWenkuFix1/js/libs/zip.min.js
Lingzu0dayWenkuFix1/js/plugins/__init__.py
Lingzu0dayWenkuFix1/js/plugins/hypothesis.js
Lingzu0dayWenkuFix1/js/plugins/search.js
lingzu_0day_wenku_fix1-2025.3.24.0.dist-info/METADATA
lingzu_0day_wenku_fix1-2025.3.24.0.dist-info/WHEEL
lingzu_0day_wenku_fix1-2025.3.24.0.dist-info/entry_points.txt
lingzu_0day_wenku_fix1-2025.3.24.0.dist-info/top_level.txt
lingzu_0day_wenku_fix1-2025.3.24.0.dist-info/RECORD
